Workbook

Sheet Read Me
A1: NORTHSTAR COMPONENTS LTD. — SYNTHETIC DATA PACK
A2: Purpose | B2: Demo dataset for Streamlit + n8n RAG investor Q&A prototype.
A3: Important | B3: Every company, financial value, transcript, quotation and management statement in this pack is fictional and created for demonstration.
A4: Currency | B4: ₹ crore unless a column says otherwise.
A5: Periods | B5: Six quarters from Q1 FY25 to Q2 FY26. FY = financial year; quarters are synthetic.
A6: Core scenario | B6: Q2 FY26 revenue ₹1,240 Cr; growth +12% YoY vs a synthetic Q2 FY25 comparison baseline of ₹1,107.1 Cr (used only for growth KPI). EBITDA margin 14.2%; prior-year comparison margin 17.0%; OCF ₹68 Cr; OCF down 43% YoY vs synthetic comparison OCF ₹119.3 Cr; net debt / annualised EBITDA 2.1x target scenario.
A7: Model note | B7: Quarterly statement values are intentionally simplified. EBITDA margin and group/segment headline figures are designed to support the demo. Do not present as real company data.
A8: Cash flow note | B8: Net change in cash = operating CF - capex - acquisitions + debt issued - debt repaid - dividends. Closing cash balances are modeled separately for demonstration and may not roll perfectly due to omitted FX/other items.
A9: Debt ratio note | B9: Net debt / EBITDA uses annualised quarterly EBITDA (quarter EBITDA × 4). The ratio is a simplified run-rate metric, not a covenant calculation.
A10: Sheet guide | B10: P&L = quarterly income statement; Cash Flow = cash flow statement and drivers; Balance Sheet = selected balances; Segment Performance = segment revenue/margin; KPI Summary = headline metrics; Guidance Register = prior statements vs actual; Investor Question Bank = questions/evidence rubric; Data Dictionary = field definitions.
A11: RAG guidance | B11: Ingest .txt/.md files from transcripts/, commentary/, guidance/, knowledge/. Keep metadata_manifest.csv and chunks_seed.jsonl for citation metadata. Keep each speaker Q&A exchange in one chunk where possible.

Sheet P&L
A1: Quarter | B1: Period End | C1: Revenue | D1: COGS | E1: Gross Profit | F1: Gross Margin | G1: SG&A | H1: R&D | I1: Other OpEx | J1: EBITDA | K1: EBITDA Margin | L1: D&A | M1: EBIT | N1: Interest | O1: PBT | P1: Tax | Q1: PAT | R1: Revenue YoY % | S1: EBITDA Margin YoY Δ (pp)
A2: Q1 FY25 | B2: 2024-06-30 | C2: 900 | D2: 603 | E2: =C2-D2 | F2: =E2/C2 | G2: 112 | H2: 22 | I2: 8 | J2: =E2-G2-H2-I2 | K2: =J2/C2 | L2: 28 | M2: =J2-L2 | N2: 12 | O2: =M2-N2 | P2: 29 | Q2: =O2-P2
A3: Q2 FY25 | B3: 2024-09-30 | C3: 940 | D3: 630 | E3: =C3-D3 | F3: =E3/C3 | G3: 116 | H3: 23 | I3: 11.2 | J3: =E3-G3-H3-I3 | K3: =J3/C3 | L3: 29 | M3: =J3-L3 | N3: 13 | O3: =M3-N3 | P3: 31 | Q3: =O3-P3 | R3: 0.044444444 | S3: 0.01
A4: Q3 FY25 | B4: 2024-12-31 | C4: 970 | D4: 650 | E4: =C4-D4 | F4: =E4/C4 | G4: 120 | H4: 24 | I4: 10 | J4: =E4-G4-H4-I4 | K4: =J4/C4 | L4: 30 | M4: =J4-L4 | N4: 13 | O4: =M4-N4 | P4: 32 | Q4: =O4-P4
A5: Q4 FY25 | B5: 2025-03-31 | C5: 1000 | D5: 670 | E5: =C5-D5 | F5: =E5/C5 | G5: 124 | H5: 24 | I5: 10 | J5: =E5-G5-H5-I5 | K5: =J5/C5 | L5: 31 | M5: =J5-L5 | N5: 13 | O5: =M5-N5 | P5: 34 | Q5: =O5-P5
A6: Q1 FY26 | B6: 2025-06-30 | C6: 1080 | D6: 735 | E6: =C6-D6 | F6: =E6/C6 | G6: 130 | H6: 25 | I6: 12 | J6: =E6-G6-H6-I6 | K6: =J6/C6 | L6: 33 | M6: =J6-L6 | N6: 14 | O6: =M6-N6 | P6: 36 | Q6: =O6-P6
A7: Q2 FY26 | B7: 2025-09-30 | C7: 1240 | D7: 862 | E7: =C7-D7 | F7: =E7/C7 | G7: 154 | H7: 28 | I7: 19.92 | J7: =E7-G7-H7-I7 | K7: =J7/C7 | L7: 40 | M7: =J7-L7 | N7: 16 | O7: =M7-N7 | P7: 38 | Q7: =O7-P7 | R7: 0.12000289 | S7: -0.028

Sheet Cash Flow
A1: Quarter | B1: Period End | C1: Net Profit (PAT) | D1: Non-cash D&A | E1: Working Capital / Other Operating Adjustments | F1: Operating Cash Flow | G1: CapEx | H1: Acquisitions | I1: Investing Cash Flow | J1: Debt Issued | K1: Debt Repaid | L1: Dividends | M1: Financing Cash Flow | N1: Net Change in Cash | O1: Receivables | P1: Inventory | Q1: Payables | R1: Receivables Days (approx) | S1: Inventory Days (approx) | T1: Payables Days (approx)
A2: Q1 FY25 | B2: 2024-06-30 | C2: ='P&L'!Q2 | D2: 28 | E2: -26 | F2: 88 | G2: 48 | H2: 0 | I2: =-G2-H2 | J2: 15 | K2: 20 | L2: 5 | M2: =J2-K2-L2 | N2: =F2+I2+M2 | O2: 205 | P2: 240 | Q2: 180 | R2: 20.5 | S2: 35.8 | T2: 26.9
A3: Q2 FY25 | B3: 2024-09-30 | C3: ='P&L'!Q3 | D3: 29 | E3: -23.8 | F3: 92 | G3: 55 | H3: 0 | I3: =-G3-H3 | J3: 0 | K3: 20 | L3: 5 | M3: =J3-K3-L3 | N3: =F3+I3+M3 | O3: 220 | P3: 255 | Q3: 188 | R3: 21.1 | S3: 36.4 | T3: 26.9
A4: Q3 FY25 | B4: 2024-12-31 | C4: ='P&L'!Q4 | D4: 30 | E4: -25 | F4: 96 | G4: 60 | H4: 5 | I4: =-G4-H4 | J4: 0 | K4: 15 | L4: 5 | M4: =J4-K4-L4 | N4: =F4+I4+M4 | O4: 232 | P4: 270 | Q4: 195 | R4: 21.5 | S4: 37.4 | T4: 27
A5: Q4 FY25 | B5: 2025-03-31 | C5: ='P&L'!Q5 | D5: 31 | E5: -20 | F5: 105 | G5: 65 | H5: 0 | I5: =-G5-H5 | J5: 0 | K5: 20 | L5: 6 | M5: =J5-K5-L5 | N5: =F5+I5+M5 | O5: 245 | P5: 282 | Q5: 205 | R5: 22.1 | S5: 37.9 | T5: 27.5
A6: Q1 FY26 | B6: 2025-06-30 | C6: ='P&L'!Q6 | D6: 33 | E6: -46 | F6: 82 | G6: 72 | H6: 0 | I6: =-G6-H6 | J6: 20 | K6: 10 | L6: 6 | M6: =J6-K6-L6 | N6: =F6+I6+M6 | O6: 275 | P6: 310 | Q6: 212 | R6: 22.9 | S6: 38 | T6: 26
A7: Q2 FY26 | B7: 2025-09-30 | C7: ='P&L'!Q7 | D7: 40 | E7: -54.08 | F7: 68 | G7: 90 | H7: 10 | I7: =-G7-H7 | J7: 40 | K7: 10 | L7: 8 | M7: =J7-K7-L7 | N7: =F7+I7+M7 | O7: 340 | P7: 365 | Q7: 224 | R7: 24.7 | S7: 38.1 | T7: 23.4

Sheet Balance Sheet
A1: Quarter | B1: Period End | C1: Cash | D1: Gross Debt | E1: Net Debt | F1: Net Debt / Annualised EBITDA | G1: Receivables | H1: Inventory | I1: Payables | J1: Total Assets (illustrative) | K1: Total Liabilities (illustrative) | L1: Equity (illustrative)
A2: Q1 FY25 | B2: 2024-06-30 | C2: 180 | D2: 520 | E2: =D2-C2 | F2: =E2/('P&L'!J2*4) | G2: 205 | H2: 240 | I2: 180 | J2: 1580 | K2: 900 | L2: 680
A3: Q2 FY25 | B3: 2024-09-30 | C3: 177 | D3: 500 | E3: =D3-C3 | F3: =E3/('P&L'!J3*4) | G3: 220 | H3: 255 | I3: 188 | J3: 1605 | K3: 894 | L3: 711
A4: Q3 FY25 | B4: 2024-12-31 | C4: 161 | D4: 485 | E4: =D4-C4 | F4: =E4/('P&L'!J4*4) | G4: 232 | H4: 270 | I4: 195 | J4: 1630 | K4: 887 | L4: 743
A5: Q4 FY25 | B5: 2025-03-31 | C5: 160 | D5: 465 | E5: =D5-C5 | F5: =E5/('P&L'!J5*4) | G5: 245 | H5: 282 | I5: 205 | J5: 1660 | K5: 880 | L5: 780
A6: Q1 FY26 | B6: 2025-06-30 | C6: 174 | D6: 475 | E6: =D6-C6 | F6: =E6/('P&L'!J6*4) | G6: 275 | H6: 310 | I6: 212 | J6: 1720 | K6: 900 | L6: 820
A7: Q2 FY26 | B7: 2025-09-30 | C7: 164 | D7: 505 | E7: =D7-C7 | F7: =E7/('P&L'!J7*4) | G7: 340 | H7: 365 | I7: 224 | J7: 1830 | K7: 970 | L7: 860

Sheet Segment Performance
A1: Quarter | B1: Segment | C1: Revenue | D1: YoY Growth | E1: EBITDA Margin | F1: EBITDA (derived) | G1: Management / interpretation note
A2: Q1 FY25 | B2: Components | C2: 171 | E2: 0.112 | F2: =C2*E2 | G2: Synthetic historical segment estimate; use for prototype trend exploration only.
A3: Q1 FY25 | B3: Industrial Systems | C3: 450 | E3: 0.185 | F3: =C3*E3 | G3: Synthetic historical segment estimate; use for prototype trend exploration only.
A4: Q1 FY25 | B4: Mobility Solutions | C4: 279 | E4: 0.14 | F4: =C4*E4 | G4: Synthetic historical segment estimate; use for prototype trend exploration only.
A5: Q2 FY25 | B5: Components | C5: 178.6 | E5: 0.112 | F5: =C5*E5 | G5: Synthetic historical segment estimate; use for prototype trend exploration only.
A6: Q2 FY25 | B6: Industrial Systems | C6: 470 | E6: 0.185 | F6: =C6*E6 | G6: Synthetic historical segment estimate; use for prototype trend exploration only.
A7: Q2 FY25 | B7: Mobility Solutions | C7: 291.4 | E7: 0.14 | F7: =C7*E7 | G7: Synthetic historical segment estimate; use for prototype trend exploration only.
A8: Q3 FY25 | B8: Components | C8: 184.3 | E8: 0.108 | F8: =C8*E8 | G8: Synthetic historical segment estimate; use for prototype trend exploration only.
A9: Q3 FY25 | B9: Industrial Systems | C9: 485 | E9: 0.181 | F9: =C9*E9 | G9: Synthetic historical segment estimate; use for prototype trend exploration only.
A10: Q3 FY25 | B10: Mobility Solutions | C10: 300.7 | E10: 0.136 | F10: =C10*E10 | G10: Synthetic historical segment estimate; use for prototype trend exploration only.
A11: Q4 FY25 | B11: Components | C11: 190 | E11: 0.108 | F11: =C11*E11 | G11: Synthetic historical segment estimate; use for prototype trend exploration only.
A12: Q4 FY25 | B12: Industrial Systems | C12: 500 | E12: 0.181 | F12: =C12*E12 | G12: Synthetic historical segment estimate; use for prototype trend exploration only.
A13: Q4 FY25 | B13: Mobility Solutions | C13: 310 | E13: 0.136 | F13: =C13*E13 | G13: Synthetic historical segment estimate; use for prototype trend exploration only.
... A16: Q1 FY26 | B16: Mobility Solutions | C16: 334.8 | E16: 0.136 | F16: =C16*E16 | G16: Synthetic historical segment estimate; use for prototype trend exploration only.
A17: Q2 FY26 | B17: Components | C17: 230 | D17: 0.03 | E17: 0.094 | F17: =C17*E17 | G17: Lower growth and under-absorption of fixed costs kept margins below group average.
A18: Q2 FY26 | B18: Industrial Systems | C18: 620 | D18: 0.19 | E18: 0.168 | F18: =C18*E18 | G18: Strong order conversion; premium product mix supported margin.
A19: Q2 FY26 | B19: Mobility Solutions | C19: 390 | D19: 0.08 | E19: 0.121 | F19: =C19*E19 | G19: Growth remained positive, but launch costs and customer mix weighed on margin.

Sheet KPI Summary
A1: Metric | B1: Q2 FY26 | C1: Comparison | D1: Change | E1: Interpretation / source
A2: Revenue (₹ Cr) | B2: 1240 | C2: 1107.14 | D2: =B2/C2-1 | E2: Synthetic Q2 FY25 comparison baseline used for +12% YoY headline.
A3: EBITDA Margin | B3: 0.142 | C3: 0.17 | D3: =B3-C3 | E3: Margin down 2.8 percentage points YoY; Q2 FY26 EBITDA is approximately ₹176.1 Cr.
A4: Operating Cash Flow (₹ Cr) | B4: 68 | C4: 119.3 | D4: =B4/C4-1 | E4: OCF down 43% YoY; working-capital absorption is a key hypothesis to investigate.
A5: Net Debt / Annualised EBITDA | B5: 2.1 | C5: 1.5 | D5: =B5-C5 | E5: Latest ratio set to 2.1x headline; compare ratio is synthetic.
A6: Industrial Systems Revenue (₹ Cr) | B6: 620 | C6: 521.01 | D6: =B6/C6-1 | E6: Latest segment; margin 16.8%.
A7: Mobility Solutions Revenue (₹ Cr) | B7: 390 | C7: 361.11 | D7: =B7/C7-1 | E7: Latest segment; margin 12.1%.
A8: Components Revenue (₹ Cr) | B8: 230 | C8: 225.02 | D8: =B8/C8-1 | E8: Latest segment; margin 9.4%.

Sheet Guidance Register
A1: Guidance ID | B1: Date Issued | C1: Quarter Issued | D1: Topic | E1: Exact fictional management wording | F1: Target / expectation | G1: Due By | H1: Latest Actual / Status | I1: Assessment | J1: Evidence Document ID
A2: G-001 | B2: 2025-03-31 | C2: Q4 FY25 | D2: Input costs / margins | E2: “We expect the current input-cost pressure to ease progressively during the first half of FY26, with margin recovery visible by Q2 FY26, assuming supplier prices normalise.” | F2: Margin recovery visible by Q2 FY26 | G2: Q2 FY26 | H2: Q2 FY26 EBITDA margin 14.2% vs 17.0% comparison baseline | I2: Potential guidance gap: actual margin remains below prior-year level; requires quantified bridge and confirmation of what assumptions changed. | J2: TR-Q4FY25
A3: G-002 | B3: 2025-06-30 | C3: Q1 FY26 | D3: Working capital | E3: “Receivables are temporarily elevated due to shipment timing. We expect collections to normalise over the next quarter.” | F3: Receivables normalise by Q2 FY26 | G3: Q2 FY26 | H3: Receivables increased to ₹340 Cr in Q2 FY26; OCF ₹68 Cr | I3: Potential gap: latest receivables are elevated; ask for ageing and collections evidence. | J3: TR-Q1FY26
A4: G-003 | B4: 2025-06-30 | C4: Q1 FY26 | D4: CapEx | E4: “We anticipate elevated capital expenditure in the first half, followed by a more measured run-rate in the second half.” | F4: CapEx moderates after H1 | G4: H2 FY26 | H4: Q2 FY26 CapEx ₹90 Cr | I4: Not yet testable against full H2; ask for updated CapEx phasing, do not assert that it has moderated. | J4: TR-Q1FY26
A5: G-004 | B5: 2025-03-31 | C5: Q4 FY25 | D5: Revenue | E5: “For FY26, we are targeting low-double-digit revenue growth, subject to customer demand and the timing of new-program ramps.” | F5: Low-double-digit revenue growth | G5: FY26 | H5: Q2 FY26 revenue ₹1,240 Cr; synthetic YoY headline +12% | I5: Directionally consistent for the quarter; full-year outcome not yet established. | J5: TR-Q4FY25
A6: G-005 | B6: 2025-09-30 | C6: Q2 FY26 | D6: Margin drivers | E6: “The margin shortfall reflects a mix of input costs, launch expenses and lower fixed-cost absorption in Components; we are quantifying the contribution of each factor.” | F6: Publish quantified bridge when validated | G6: Next update | H6: No quantified bridge provided in this synthetic pack | I6: Evidence gap: don't invent contribution percentages; request validated price-volume-mix and cost bridge. | J6: TR-Q2FY26

Sheet Investor Question Bank
A1: Question ID | B1: Risk Score (1-5) | C1: Priority | D1: Investor question | E1: Trigger / metric | F1: Evidence required | G1: Safe answer scaffold | H1: Escalation / evidence gap
A2: Q-001 | B2: 5 | C2: Critical | D2: Revenue grew 12%, so why did EBITDA margin fall 280 bps versus the prior-year comparison? | E2: Revenue +12%; EBITDA margin 14.2% vs 17.0% | F2: Price-volume-mix bridge; raw-material inflation; launch expenses; segment mix; fixed-cost absorption; exact prior guidance | G2: Acknowledge the 280 bps decline; describe only verified drivers; quantify each driver only after Finance validates the bridge; distinguish temporary from structural. | H2: No quantified driver bridge in source pack; escalate to CFO/FP&A.
A3: Q-002 | B3: 5 | C3: Critical | D3: Why did operating cash flow fall 43% while revenue increased? | E3: OCF ₹68 Cr; down 43% YoY | F3: Receivables ageing, inventory days, payables, customer collections, PAT-to-OCF reconciliation | G3: State reported OCF and identify verified working-capital movements; do not attribute the full decline to one driver without a reconciliation. | H3: Need validated working-capital bridge and cash conversion cycle.
A4: Q-003 | B4: 5 | C4: Critical | D4: You previously expected margin recovery by Q2 FY26. What changed? | E4: Prior guidance G-001 vs actual margin | F4: Q4 FY25 transcript exact quote; Q1/Q2 commentary; updated cost assumptions; current margin bridge | G4: Acknowledge prior wording and compare with actual outcome; explain changes only where documented; state what is still being validated. | H4: Prior statement exists; quantified variance explanation is incomplete.
A5: Q-004 | B5: 4 | C5: High | D5: Receivables were described as temporary. Why are they now ₹340 Cr? | E5: Receivables ₹340 Cr; OCF pressure | F5: Ageing buckets, top-customer balances, post-quarter collections, overdue % | G5: Give the balance and collection status only if verified; commit to a dated follow-up only if approved. | H5: No ageing schedule/post-quarter collection data.
A6: Q-005 | B6: 4 | C6: High | D6: Which segment is causing the most pressure on group profitability? | E6: Segment margins: 16.8%, 12.1%, 9.4% | F6: Segment EBITDA contributions and changes in mix, not margin alone | G6: Explain segment-level margin dispersion and contribution using disclosed values; do not equate lowest margin with largest absolute drag without calculation. | H6: Need historical segment profit bridge for precise attribution.
A7: Q-006 | B7: 4 | C7: High | D7: Will CapEx and leverage rise further? | E7: CapEx ₹90 Cr; net debt/EBITDA 2.1x | F7: Approved CapEx plan, debt maturities, liquidity, covenant headroom, guidance approval | G7: Use approved public guidance only; separate current fact from forward-looking statement and conditions. | H7: No approved updated leverage/CapEx outlook in pack.
A8: Q-007 | B8: 3 | C8: Medium | D8: Is the revenue growth broad-based or concentrated in one segment? | E8: Segment revenue growth 19%, 8%, 3% | F8: Segment growth history; orders/backlog; customer concentration | G8: Describe the three segment growth rates and state limits of available order/backlog evidence. | H8: Need order book and customer concentration data.

Sheet Data Dictionary
A1: Field / metric | B1: Definition | C1: Unit | D1: Source / calculation | E1: Caveat
A2: Revenue | B2: Quarterly revenue | C2: ₹ Cr | D2: Synthetic P&L | E2: Fictional
A3: COGS | B3: Cost of goods sold | C3: ₹ Cr | D3: Synthetic P&L | E3: Simplified
A4: Gross Profit | B4: Revenue minus COGS | C4: ₹ Cr | D4: Formula
A5: EBITDA | B5: Gross profit less SG&A, R&D and other operating expenses | C5: ₹ Cr | D5: Formula | E5: D&A excluded
A6: EBITDA Margin | B6: EBITDA / Revenue | C6: % | D6: Formula | E6: Latest set to 14.2%; compare baseline set to 17.0%
A7: Operating Cash Flow | B7: Net cash from operating activities | C7: ₹ Cr | D7: Synthetic cash flow | E7: Q2 FY26 ₹68 Cr headline; down 43% vs synthetic baseline
A8: Free Cash Flow | B8: Operating cash flow minus CapEx | C8: ₹ Cr | D8: Formula | E8: Simplified; excludes asset disposals
A9: Net Debt | B9: Gross debt minus cash | C9: ₹ Cr | D9: Formula
A10: Net Debt / Annualised EBITDA | B10: Net debt / (quarter EBITDA × 4) | C10: x | D10: Formula | E10: Headline comparison ratio may use a separate illustrative baseline
A11: Receivables Days | B11: Receivables / quarterly revenue × 90 | C11: days | D11: Approximation | E11: Uses 90-day quarter
A12: Inventory Days | B12: Inventory / quarterly COGS × 90 | C12: days | D12: Approximation | E12: Uses 90-day quarter
A13: Guidance Gap | B13: Prior explicit statement compared with current disclosed result | C13: text | D13: Guidance Register + transcripts | E13: Do not infer intent or claim breach without context
A14: Evidence status | B14: Supported / partial / missing | C14: label | D14: RAG review | E14: Mark missing data explicitly

Sheet Assumptions
A1: Assumption ID | B1: Assumption | C1: Value | D1: Why / caveat
A2: A-001 | B2: Company | C2: Northstar Components Ltd. | D2: Fictional name; no real-company data.
A3: A-002 | B3: Latest quarter | C3: Q2 FY26 | D3: Synthetic period ending 2025-09-30.
A4: A-003 | B4: Revenue YoY comparison baseline | C4: 1107.14 | D4: Chosen so ₹1,240 Cr implies approximately +12% YoY.
A5: A-004 | B5: EBITDA margin comparison baseline | C5: 0.17 | D5: Chosen to demonstrate a 280 bps decline to 14.2%.
A6: A-005 | B6: OCF comparison baseline | C6: 119.3 | D6: Chosen so ₹68 Cr is approximately 43% lower.
A7: A-006 | B7: Net debt / EBITDA headline | C7: 2.1 | D7: Headline demo KPI; the simplified historical debt math may differ slightly; use the headline KPI sheet for the assignment scenario.
A8: A-007 | B8: Unit | C8: ₹ crore | D8: Except ratios, percentages and days.
A9: A-008 | B9: Synthetic data notice | C9: All numbers and quotes are fictional | D9: Never use as real investment advice or company disclosure.
